odoo8_addon_crm_lead_sale_link-8.0.1.0.0.99.dev24-py3.8-nspkg.pth
odoo_addons/crm_lead_sale_link/README.rst
odoo_addons/crm_lead_sale_link/__init__.py
odoo_addons/crm_lead_sale_link/__openerp__.py
odoo_addons/crm_lead_sale_link/i18n/bg.po
odoo_addons/crm_lead_sale_link/i18n/ca.po
odoo_addons/crm_lead_sale_link/i18n/crm_lead_sale_link.pot
odoo_addons/crm_lead_sale_link/i18n/de.po
odoo_addons/crm_lead_sale_link/i18n/es.po
odoo_addons/crm_lead_sale_link/i18n/es_ES.po
odoo_addons/crm_lead_sale_link/i18n/fi.po
odoo_addons/crm_lead_sale_link/i18n/fr.po
odoo_addons/crm_lead_sale_link/i18n/hr.po
odoo_addons/crm_lead_sale_link/i18n/hu.po
odoo_addons/crm_lead_sale_link/i18n/it.po
odoo_addons/crm_lead_sale_link/i18n/nl.po
odoo_addons/crm_lead_sale_link/i18n/nl_NL.po
odoo_addons/crm_lead_sale_link/i18n/pt_BR.po
odoo_addons/crm_lead_sale_link/i18n/ro.po
odoo_addons/crm_lead_sale_link/i18n/sk.po
odoo_addons/crm_lead_sale_link/i18n/sl.po
odoo_addons/crm_lead_sale_link/i18n/tr.po
odoo_addons/crm_lead_sale_link/i18n/tr_TR.po
odoo_addons/crm_lead_sale_link/i18n/zh_CN.po
odoo_addons/crm_lead_sale_link/models/__init__.py
odoo_addons/crm_lead_sale_link/models/crm_lead.py
odoo_addons/crm_lead_sale_link/static/description/icon.png
odoo_addons/crm_lead_sale_link/static/description/icon.svg
odoo_addons/crm_lead_sale_link/views/crm_lead_view.xml
odoo8_addon_crm_lead_sale_link-8.0.1.0.0.99.dev24.dist-info/METADATA
odoo8_addon_crm_lead_sale_link-8.0.1.0.0.99.dev24.dist-info/WHEEL
odoo8_addon_crm_lead_sale_link-8.0.1.0.0.99.dev24.dist-info/namespace_packages.txt
odoo8_addon_crm_lead_sale_link-8.0.1.0.0.99.dev24.dist-info/top_level.txt
odoo8_addon_crm_lead_sale_link-8.0.1.0.0.99.dev24.dist-info/RECORD
